README.md
setup.py
HarperDB_SDK.egg-info/PKG-INFO
HarperDB_SDK.egg-info/SOURCES.txt
HarperDB_SDK.egg-info/dependency_links.txt
HarperDB_SDK.egg-info/requires.txt
HarperDB_SDK.egg-info/top_level.txt
harperdb/__init__.py
harperdb/exceptions.py
harperdb/harperdb.py
harperdb/wrappers.py