Metadata-Version: 2.1
Name: HarperDB-SDK
Version: 0.2.0
Summary: Simple SDK for HarperDB.
Home-page: https://github.com/harperdb/harperdb-sdk-python
Author: Tom Young
Author-email: shadetreemetalworks@gmail.com
Maintainer: HarperDB
Maintainer-email: hello@harperdb.io
License: UNKNOWN
Platform: UNKNOWN
Classifier: Programming Language :: Python :: 3
Classifier: License :: OSI Approved :: MIT License
Classifier: Operating System :: OS Independent
Requires-Python: >=3.4
